GitReference/README.md
GitReference/__init__.py
GitReference/__main__.py
GitReference/file.epub
GitReference/index.html
GitReference/css/__init__.py
GitReference/css/annotations.css
GitReference/css/main.css
GitReference/css/normalize.css
GitReference/css/popup.css
GitReference/font/__init__.py
GitReference/font/fontello.eot
GitReference/font/fontello.svg
GitReference/font/fontello.ttf
GitReference/font/fontello.woff
GitReference/img/__init__.py
GitReference/img/annotator-glyph-sprite.png
GitReference/img/annotator-icon-sprite.png
GitReference/img/apple-touch-icon.png
GitReference/img/cancelfullscreen.png
GitReference/img/close.png
GitReference/img/fullscreen.png
GitReference/img/loader.gif
GitReference/img/menu-icon.png
GitReference/img/save.png
GitReference/img/saved.png
GitReference/img/settings-s.png
GitReference/img/settings.png
GitReference/img/star.png
GitReference/js/__init__.py
GitReference/js/epub.js
GitReference/js/epub.min.js
GitReference/js/epub.min.map
GitReference/js/hooks.min.js
GitReference/js/hooks.min.map
GitReference/js/reader.js
GitReference/js/reader.js.map
GitReference/js/reader.min.js
GitReference/js/reader.min.map
GitReference/js/hooks/__init__.py
GitReference/js/hooks/extensions/__init__.py
GitReference/js/hooks/extensions/highlight.js
GitReference/js/libs/__init__.py
GitReference/js/libs/jquery.min.js
GitReference/js/libs/localforage.min.js
GitReference/js/libs/screenfull.js
GitReference/js/libs/screenfull.min.js
GitReference/js/libs/zip.min.js
GitReference/js/plugins/__init__.py
GitReference/js/plugins/hypothesis.js
GitReference/js/plugins/search.js
git_reference-2024.3.1.0.dist-info/METADATA
git_reference-2024.3.1.0.dist-info/WHEEL
git_reference-2024.3.1.0.dist-info/entry_points.txt
git_reference-2024.3.1.0.dist-info/top_level.txt
git_reference-2024.3.1.0.dist-info/RECORD
